MANIFEST.in
setup.py
bin/den
denim/__init__.py
denim/api.py
denim/constants.py
denim/decorators.py
denim/environment.py
denim/paths.py
denim/pip.py
denim/recipes.py
denim/system.py
denim/utils.py
denim/virtualenv.py
denim.egg-info/PKG-INFO
denim.egg-info/SOURCES.txt
denim.egg-info/dependency_links.txt
denim.egg-info/top_level.txt
denim/django/__init__.py
denim/django/south.py
denim/package/__init__.py
denim/package/debian.py
denim/scaffold/__init__.py
denim/scm/__init__.py
denim/scm/git.py
denim/scm/hg.py
denim/service/__init__.py
denim/service/supervisor.py
denim/webserver/__init__.py
denim/webserver/apache.py
denim/webserver/nginx.py