Metadata-Version: 1.1
Name: denim
Version: 0.1.2b1
Summary: A Fabric deployment strategy for Python web applications.
Home-page: http://bitbucket.org/timsavage/denim
Author: Tim Savage
Author-email: tim.savage@poweredbypenguins.org
License: UNKNOWN
Platform: UNKNOWN
Classifier: Development Status :: 4 - Beta
Classifier: Programming Language :: Python
Requires: fabric
